timefunctions/__init__.py
just_time_it-0.1.2.dist-info/LICENSE
just_time_it-0.1.2.dist-info/METADATA
just_time_it-0.1.2.dist-info/WHEEL
just_time_it-0.1.2.dist-info/top_level.txt
just_time_it-0.1.2.dist-info/RECORD
