Metadata-Version: 2.1
Name: just-time-it
Version: 0.1.2
Summary: The fuss-free way to time functions
Home-page: https://github.com/GoldenCorgi/just-time-it
Author: GoldenCorgi
License: UNKNOWN
Platform: UNKNOWN
Classifier: Programming Language :: Python :: 3.6
Classifier: Programming Language :: Python :: 3.7
Classifier: Intended Audience :: Developers
Classifier: Operating System :: OS Independent
